archash4all.cp37-win_amd64.pyd
archash4all/__init__.py
archash4all/mainapi.py
archash4all_python-0.616b1.dist-info/LICENSE
archash4all_python-0.616b1.dist-info/METADATA
archash4all_python-0.616b1.dist-info/WHEEL
archash4all_python-0.616b1.dist-info/top_level.txt
archash4all_python-0.616b1.dist-info/RECORD
