Metadata-Version: 2.1
Name: archash4all-python
Version: 0.616b1
Summary: Generate x-random-challenge for arcapi requests
Home-page: UNKNOWN
Author: J.R w/ TheSnowfield
License: MIT License
Keywords: Python,hashing
Platform: any
Requires-Python: >=3.1
